[
  {
    "model": "blocks.lessonblockrelation",
    "pk": 4,
    "fields": {
      "lesson": 1,
      "block": 104,
      "order": 1
    }
  },
  {
    "model": "blocks.lessonblockrelation",
    "pk": 5,
    "fields": {
      "lesson": 1,
      "block": 106,
      "order": 2
    }
  },
  {
    "model": "blocks.lessonblockrelation",
    "pk": 6,
    "fields": {
      "lesson": 1,
      "block": 111,
      "order": 3
    }
  },
  {
    "model": "blocks.lessonblockrelation",
    "pk": 7,
    "fields": {
      "lesson": 1,
      "block": 113,
      "order": 4
    }
  },
  {
    "model": "blocks.lessonblockrelation",
    "pk": 8,
    "fields": {
      "lesson": 1,
      "block": 115,
      "order": 6
    }
  },
  {
    "model": "blocks.lessonblockrelation",
    "pk": 9,
    "fields": {
      "lesson": 1,
      "block": 116,
      "order": 7
    }
  },
  {
    "model": "blocks.lessonblockrelation",
    "pk": 10,
    "fields": {
      "lesson": 1,
      "block": 117,
      "order": 8
    }
  },
  {
    "model": "blocks.lessonblockrelation",
    "pk": 12,
    "fields": {
      "lesson": 2,
      "block": 119,
      "order": 1
    }
  },
  {
    "model": "blocks.lessonblockrelation",
    "pk": 13,
    "fields": {
      "lesson": 2,
      "block": 121,
      "order": 2
    }
  },
  {
    "model": "blocks.lessonblockrelation",
    "pk": 14,
    "fields": {
      "lesson": 2,
      "block": 122,
      "order": 3
    }
  },
  {
    "model": "blocks.lessonblockrelation",
    "pk": 15,
    "fields": {
      "lesson": 2,
      "block": 132,
      "order": 4
    }
  },
  {
    "model": "blocks.lessonblockrelation",
    "pk": 16,
    "fields": {
      "lesson": 2,
      "block": 133,
      "order": 6
    }
  },
  {
    "model": "blocks.lessonblockrelation",
    "pk": 17,
    "fields": {
      "lesson": 2,
      "block": 134,
      "order": 5
    }
  },
  {
    "model": "blocks.lessonblockrelation",
    "pk": 18,
    "fields": {
      "lesson": 1,
      "block": 135,
      "order": 5
    }
  },
  {
    "model": "blocks.lessonblockrelation",
    "pk": 19,
    "fields": {
      "lesson": 3,
      "block": 136,
      "order": 1
    }
  },
  {
    "model": "blocks.lessonblockrelation",
    "pk": 20,
    "fields": {
      "lesson": 3,
      "block": 137,
      "order": 2
    }
  },
  {
    "model": "blocks.lessonblockrelation",
    "pk": 21,
    "fields": {
      "lesson": 3,
      "block": 138,
      "order": 4
    }
  },
  {
    "model": "blocks.lessonblockrelation",
    "pk": 22,
    "fields": {
      "lesson": 3,
      "block": 139,
      "order": 5
    }
  },
  {
    "model": "blocks.lessonblockrelation",
    "pk": 23,
    "fields": {
      "lesson": 3,
      "block": 140,
      "order": 6
    }
  },
  {
    "model": "blocks.lessonblockrelation",
    "pk": 24,
    "fields": {
      "lesson": 3,
      "block": 141,
      "order": 7
    }
  },
  {
    "model": "blocks.lessonblockrelation",
    "pk": 25,
    "fields": {
      "lesson": 3,
      "block": 143,
      "order": 8
    }
  },
  {
    "model": "blocks.lessonblockrelation",
    "pk": 26,
    "fields": {
      "lesson": 3,
      "block": 100,
      "order": 9
    }
  },
  {
    "model": "blocks.lessonblockrelation",
    "pk": 27,
    "fields": {
      "lesson": 3,
      "block": 142,
      "order": 10
    }
  },
  {
    "model": "blocks.lessonblockrelation",
    "pk": 28,
    "fields": {
      "lesson": 3,
      "block": 144,
      "order": 3
    }
  },
  {
    "model": "blocks.lessonblockrelation",
    "pk": 29,
    "fields": {
      "lesson": 6,
      "block": 145,
      "order": 1
    }
  },
  {
    "model": "blocks.lessonblockrelation",
    "pk": 30,
    "fields": {
      "lesson": 6,
      "block": 146,
      "order": 2
    }
  },
  {
    "model": "blocks.lessonblockrelation",
    "pk": 31,
    "fields": {
      "lesson": 6,
      "block": 147,
      "order": 3
    }
  },
  {
    "model": "blocks.lessonblockrelation",
    "pk": 32,
    "fields": {
      "lesson": 6,
      "block": 46,
      "order": 4
    }
  },
  {
    "model": "blocks.lessonblockrelation",
    "pk": 33,
    "fields": {
      "lesson": 6,
      "block": 43,
      "order": 5
    }
  },
  {
    "model": "blocks.lessonblockrelation",
    "pk": 34,
    "fields": {
      "lesson": 6,
      "block": 83,
      "order": 6
    }
  },
  {
    "model": "blocks.lessonblockrelation",
    "pk": 35,
    "fields": {
      "lesson": 6,
      "block": 85,
      "order": 7
    }
  },
  {
    "model": "blocks.lessonblockrelation",
    "pk": 36,
    "fields": {
      "lesson": 6,
      "block": 92,
      "order": 8
    }
  },
  {
    "model": "blocks.lessonblockrelation",
    "pk": 37,
    "fields": {
      "lesson": 6,
      "block": 15,
      "order": 9
    }
  },
  {
    "model": "blocks.lessonblockrelation",
    "pk": 38,
    "fields": {
      "lesson": 6,
      "block": 154,
      "order": 10
    }
  },
  {
    "model": "blocks.lessonblockrelation",
    "pk": 39,
    "fields": {
      "lesson": 7,
      "block": 148,
      "order": 1
    }
  },
  {
    "model": "blocks.lessonblockrelation",
    "pk": 40,
    "fields": {
      "lesson": 7,
      "block": 149,
      "order": 2
    }
  },
  {
    "model": "blocks.lessonblockrelation",
    "pk": 41,
    "fields": {
      "lesson": 7,
      "block": 22,
      "order": 4
    }
  },
  {
    "model": "blocks.lessonblockrelation",
    "pk": 42,
    "fields": {
      "lesson": 7,
      "block": 27,
      "order": 5
    }
  },
  {
    "model": "blocks.lessonblockrelation",
    "pk": 43,
    "fields": {
      "lesson": 7,
      "block": 44,
      "order": 6
    }
  },
  {
    "model": "blocks.lessonblockrelation",
    "pk": 44,
    "fields": {
      "lesson": 7,
      "block": 155,
      "order": 7
    }
  },
  {
    "model": "blocks.lessonblockrelation",
    "pk": 45,
    "fields": {
      "lesson": 7,
      "block": 156,
      "order": 3
    }
  },
  {
    "model": "blocks.lessonblockrelation",
    "pk": 46,
    "fields": {
      "lesson": 8,
      "block": 150,
      "order": 1
    }
  },
  {
    "model": "blocks.lessonblockrelation",
    "pk": 47,
    "fields": {
      "lesson": 8,
      "block": 151,
      "order": 2
    }
  },
  {
    "model": "blocks.lessonblockrelation",
    "pk": 48,
    "fields": {
      "lesson": 8,
      "block": 152,
      "order": 3
    }
  },
  {
    "model": "blocks.lessonblockrelation",
    "pk": 49,
    "fields": {
      "lesson": 8,
      "block": 153,
      "order": 4
    }
  },
  {
    "model": "blocks.lessonblockrelation",
    "pk": 50,
    "fields": {
      "lesson": 8,
      "block": 157,
      "order": 5
    }
  },
  {
    "model": "blocks.lessonblockrelation",
    "pk": 51,
    "fields": {
      "lesson": 8,
      "block": 158,
      "order": 6
    }
  },
  {
    "model": "blocks.lessonblockrelation",
    "pk": 52,
    "fields": {
      "lesson": 18,
      "block": 159,
      "order": 1
    }
  },
  {
    "model": "blocks.lessonblockrelation",
    "pk": 54,
    "fields": {
      "lesson": 18,
      "block": 161,
      "order": 2
    }
  },
  {
    "model": "blocks.lessonblockrelation",
    "pk": 55,
    "fields": {
      "lesson": 18,
      "block": 162,
      "order": 3
    }
  },
  {
    "model": "blocks.lessonblockrelation",
    "pk": 56,
    "fields": {
      "lesson": 19,
      "block": 160,
      "order": 1
    }
  },
  {
    "model": "blocks.lessonblockrelation",
    "pk": 57,
    "fields": {
      "lesson": 20,
      "block": 167,
      "order": 1
    }
  },
  {
    "model": "blocks.lessonblockrelation",
    "pk": 58,
    "fields": {
      "lesson": 20,
      "block": 168,
      "order": 2
    }
  },
  {
    "model": "blocks.lessonblockrelation",
    "pk": 59,
    "fields": {
      "lesson": 20,
      "block": 169,
      "order": 3
    }
  },
  {
    "model": "blocks.lessonblockrelation",
    "pk": 60,
    "fields": {
      "lesson": 21,
      "block": 170,
      "order": 1
    }
  },
  {
    "model": "blocks.lessonblockrelation",
    "pk": 61,
    "fields": {
      "lesson": 21,
      "block": 171,
      "order": 2
    }
  },
  {
    "model": "blocks.lessonblockrelation",
    "pk": 62,
    "fields": {
      "lesson": 21,
      "block": 172,
      "order": 3
    }
  },
  {
    "model": "blocks.lessonblockrelation",
    "pk": 63,
    "fields": {
      "lesson": 21,
      "block": 173,
      "order": 4
    }
  },
  {
    "model": "blocks.lessonblockrelation",
    "pk": 64,
    "fields": {
      "lesson": 21,
      "block": 174,
      "order": 5
    }
  },
  {
    "model": "blocks.lessonblockrelation",
    "pk": 65,
    "fields": {
      "lesson": 21,
      "block": 175,
      "order": 6
    }
  },
  {
    "model": "blocks.lessonblockrelation",
    "pk": 66,
    "fields": {
      "lesson": 22,
      "block": 176,
      "order": 1
    }
  },
  {
    "model": "blocks.lessonblockrelation",
    "pk": 67,
    "fields": {
      "lesson": 19,
      "block": 163,
      "order": 2
    }
  },
  {
    "model": "blocks.lessonblockrelation",
    "pk": 68,
    "fields": {
      "lesson": 19,
      "block": 164,
      "order": 3
    }
  },
  {
    "model": "blocks.lessonblockrelation",
    "pk": 69,
    "fields": {
      "lesson": 19,
      "block": 165,
      "order": 4
    }
  },
  {
    "model": "blocks.lessonblockrelation",
    "pk": 70,
    "fields": {
      "lesson": 19,
      "block": 166,
      "order": 5
    }
  },
  {
    "model": "blocks.lessonblockrelation",
    "pk": 71,
    "fields": {
      "lesson": 18,
      "block": 179,
      "order": 4
    }
  },
  {
    "model": "blocks.lessonblockrelation",
    "pk": 72,
    "fields": {
      "lesson": 18,
      "block": 178,
      "order": 5
    }
  },
  {
    "model": "blocks.lessonblockrelation",
    "pk": 73,
    "fields": {
      "lesson": 18,
      "block": 177,
      "order": 6
    }
  },
  {
    "model": "blocks.lessonblockrelation",
    "pk": 74,
    "fields": {
      "lesson": 19,
      "block": 180,
      "order": 6
    }
  },
  {
    "model": "blocks.lessonblockrelation",
    "pk": 75,
    "fields": {
      "lesson": 19,
      "block": 181,
      "order": 7
    }
  },
  {
    "model": "blocks.lessonblockrelation",
    "pk": 76,
    "fields": {
      "lesson": 20,
      "block": 56,
      "order": 4
    }
  },
  {
    "model": "blocks.lessonblockrelation",
    "pk": 77,
    "fields": {
      "lesson": 20,
      "block": 182,
      "order": 5
    }
  },
  {
    "model": "blocks.lessonblockrelation",
    "pk": 78,
    "fields": {
      "lesson": 20,
      "block": 183,
      "order": 6
    }
  },
  {
    "model": "blocks.lessonblockrelation",
    "pk": 79,
    "fields": {
      "lesson": 20,
      "block": 184,
      "order": 7
    }
  },
  {
    "model": "blocks.lessonblockrelation",
    "pk": 80,
    "fields": {
      "lesson": 21,
      "block": 59,
      "order": 7
    }
  },
  {
    "model": "blocks.lessonblockrelation",
    "pk": 81,
    "fields": {
      "lesson": 21,
      "block": 2,
      "order": 8
    }
  },
  {
    "model": "blocks.lessonblockrelation",
    "pk": 82,
    "fields": {
      "lesson": 21,
      "block": 4,
      "order": 9
    }
  },
  {
    "model": "blocks.lessonblockrelation",
    "pk": 83,
    "fields": {
      "lesson": 21,
      "block": 5,
      "order": 10
    }
  },
  {
    "model": "blocks.lessonblockrelation",
    "pk": 84,
    "fields": {
      "lesson": 22,
      "block": 185,
      "order": 2
    }
  },
  {
    "model": "blocks.lessonblockrelation",
    "pk": 85,
    "fields": {
      "lesson": 22,
      "block": 186,
      "order": 3
    }
  },
  {
    "model": "blocks.lessonblockrelation",
    "pk": 86,
    "fields": {
      "lesson": 23,
      "block": 187,
      "order": 1
    }
  },
  {
    "model": "blocks.lessonblockrelation",
    "pk": 87,
    "fields": {
      "lesson": 23,
      "block": 188,
      "order": 2
    }
  },
  {
    "model": "blocks.lessonblockrelation",
    "pk": 88,
    "fields": {
      "lesson": 23,
      "block": 70,
      "order": 3
    }
  },
  {
    "model": "blocks.lessonblockrelation",
    "pk": 89,
    "fields": {
      "lesson": 23,
      "block": 72,
      "order": 4
    }
  },
  {
    "model": "blocks.lessonblockrelation",
    "pk": 90,
    "fields": {
      "lesson": 23,
      "block": 73,
      "order": 5
    }
  },
  {
    "model": "blocks.lessonblockrelation",
    "pk": 91,
    "fields": {
      "lesson": 23,
      "block": 189,
      "order": 6
    }
  },
  {
    "model": "blocks.lessonblockrelation",
    "pk": 92,
    "fields": {
      "lesson": 24,
      "block": 190,
      "order": 1
    }
  },
  {
    "model": "blocks.lessonblockrelation",
    "pk": 93,
    "fields": {
      "lesson": 24,
      "block": 191,
      "order": 2
    }
  },
  {
    "model": "blocks.lessonblockrelation",
    "pk": 94,
    "fields": {
      "lesson": 24,
      "block": 192,
      "order": 3
    }
  },
  {
    "model": "blocks.lessonblockrelation",
    "pk": 95,
    "fields": {
      "lesson": 24,
      "block": 193,
      "order": 4
    }
  },
  {
    "model": "blocks.lessonblockrelation",
    "pk": 96,
    "fields": {
      "lesson": 24,
      "block": 194,
      "order": 5
    }
  },
  {
    "model": "blocks.lessonblockrelation",
    "pk": 97,
    "fields": {
      "lesson": 24,
      "block": 195,
      "order": 6
    }
  },
  {
    "model": "blocks.lessonblockrelation",
    "pk": 98,
    "fields": {
      "lesson": 24,
      "block": 196,
      "order": 7
    }
  },
  {
    "model": "blocks.lessonblockrelation",
    "pk": 99,
    "fields": {
      "lesson": 24,
      "block": 197,
      "order": 8
    }
  },
  {
    "model": "blocks.lessonblockrelation",
    "pk": 100,
    "fields": {
      "lesson": 24,
      "block": 198,
      "order": 9
    }
  },
  {
    "model": "blocks.lessonblockrelation",
    "pk": 101,
    "fields": {
      "lesson": 24,
      "block": 199,
      "order": 10
    }
  },
  {
    "model": "blocks.lessonblockrelation",
    "pk": 102,
    "fields": {
      "lesson": 24,
      "block": 200,
      "order": 11
    }
  },
  {
    "model": "blocks.lessonblockrelation",
    "pk": 103,
    "fields": {
      "lesson": 25,
      "block": 201,
      "order": 1
    }
  },
  {
    "model": "blocks.lessonblockrelation",
    "pk": 104,
    "fields": {
      "lesson": 25,
      "block": 202,
      "order": 2
    }
  },
  {
    "model": "blocks.lessonblockrelation",
    "pk": 105,
    "fields": {
      "lesson": 25,
      "block": 203,
      "order": 3
    }
  },
  {
    "model": "blocks.lessonblockrelation",
    "pk": 106,
    "fields": {
      "lesson": 25,
      "block": 204,
      "order": 4
    }
  },
  {
    "model": "blocks.lessonblockrelation",
    "pk": 107,
    "fields": {
      "lesson": 25,
      "block": 205,
      "order": 5
    }
  },
  {
    "model": "blocks.lessonblockrelation",
    "pk": 108,
    "fields": {
      "lesson": 25,
      "block": 206,
      "order": 6
    }
  },
  {
    "model": "blocks.lessonblockrelation",
    "pk": 109,
    "fields": {
      "lesson": 25,
      "block": 207,
      "order": 7
    }
  },
  {
    "model": "blocks.lessonblockrelation",
    "pk": 110,
    "fields": {
      "lesson": 25,
      "block": 208,
      "order": 8
    }
  },
  {
    "model": "blocks.lessonblockrelation",
    "pk": 111,
    "fields": {
      "lesson": 25,
      "block": 209,
      "order": 9
    }
  },
  {
    "model": "blocks.lessonblockrelation",
    "pk": 112,
    "fields": {
      "lesson": 25,
      "block": 210,
      "order": 10
    }
  },
  {
    "model": "blocks.lessonblockrelation",
    "pk": 113,
    "fields": {
      "lesson": 25,
      "block": 212,
      "order": 11
    }
  },
  {
    "model": "blocks.lessonblockrelation",
    "pk": 114,
    "fields": {
      "lesson": 25,
      "block": 213,
      "order": 12
    }
  },
  {
    "model": "blocks.lessonblockrelation",
    "pk": 115,
    "fields": {
      "lesson": 25,
      "block": 211,
      "order": 13
    }
  },
  {
    "model": "blocks.lessonblockrelation",
    "pk": 116,
    "fields": {
      "lesson": 25,
      "block": 214,
      "order": 14
    }
  }
]